localaplace/__init__.py
localaplace/laplace.py
localaplace-0.0.1.dist-info/LICENSE
localaplace-0.0.1.dist-info/METADATA
localaplace-0.0.1.dist-info/WHEEL
localaplace-0.0.1.dist-info/top_level.txt
localaplace-0.0.1.dist-info/RECORD
