Metadata-Version: 2.1
Name: localaplace
Version: 0.0.1
Summary: implement of local laplace filter algorithm
Author-email: lstm-kirigaya <1193466151@qq.com>
License: Apache 2.0
Project-URL: text, https://github.com/LSTM-Kirigaya
Keywords: local laplace filter,local-laplace-filter,computer vision,tone mapping,image process
Classifier: Intended Audience :: Developers
Classifier: Operating System :: OS Independent
Classifier: Programming Language :: Python :: 3
Requires-Python: >=3.5
License-File: LICENSE
Requires-Dist: numpy
Requires-Dist: opencv-python
Requires-Dist: tqdm
